uptick/__init__.py
uptick/account.py
uptick/api.py
uptick/bip38.py
uptick/callorders.py
uptick/cli.py
uptick/committee.py
uptick/decorators.py
uptick/feed.py
uptick/htlc.py
uptick/info.py
uptick/main.py
uptick/markets.py
uptick/message.py
uptick/pools.py
uptick/proposal.py
uptick/rpc.py
uptick/ticket.py
uptick/tools.py
uptick/ui.py
uptick/vesting.py
uptick/votes.py
uptick/wallet.py
uptick/witness.py
uptick/workers.py
uptick/apis/example-config.yaml
uptick/apis/poloniex.py
uptick-0.2.6.dist-info/AUTHORS
uptick-0.2.6.dist-info/LICENSE.txt
uptick-0.2.6.dist-info/METADATA
uptick-0.2.6.dist-info/WHEEL
uptick-0.2.6.dist-info/entry_points.txt
uptick-0.2.6.dist-info/top_level.txt
uptick-0.2.6.dist-info/RECORD
