Metadata-Version: 2.1
Name: uptick
Version: 0.2.6
Summary: Command line tool to interface with the BitShares network
Home-page: http://uptick.rocks
Author: Fabian Schuh
Author-email: Fabian@chainsquad.com
Maintainer: Fabian Schuh
Maintainer-email: Fabian@chainsquad.com
License: UNKNOWN
Download-URL: https://github.com/xeroc/uptick/tarball/0.2.6
Keywords: bitshares,library,api,rpc,cli
Platform: UNKNOWN
Classifier: License :: OSI Approved :: MIT License
Classifier: Operating System :: OS Independent
Classifier: Programming Language :: Python :: 3
Classifier: Development Status :: 3 - Alpha
Classifier: Intended Audience :: Developers
Requires-Dist: bitshares (>=0.7.0)
Requires-Dist: prettytable
Requires-Dist: click
Requires-Dist: click-datetime
Requires-Dist: termcolor
Requires-Dist: tqdm
Requires-Dist: pyyaml
Requires-Dist: pygments
